bric_arduino_controllers/__init__.py
bric_arduino_controllers/arduino_scpi_controller/__init__.py
bric_arduino_controllers/arduino_scpi_controller/arduino_scpi_controller.py
bric_arduino_controllers-0.0.1.dist-info/LICENSE
bric_arduino_controllers-0.0.1.dist-info/METADATA
bric_arduino_controllers-0.0.1.dist-info/WHEEL
bric_arduino_controllers-0.0.1.dist-info/top_level.txt
bric_arduino_controllers-0.0.1.dist-info/RECORD
